{
  "Users": [
    {
      "fName": "Harry",
      "lName": "Potter",
      "idNumber": "1111",
      "phoneNumber": "111 111 1111",
      "email": "HP@hogwarts.ca",
      "password": "1234",
      "rating": 5,
      "rented": []
    },
    {
      "fName": "Hermione",
      "lName": "Granger",
      "idNumber": "2222",
      "phoneNumber": "222 222 2222",
      "email": "HG@hogwarts.ca",
      "password": "1234",
      "rating": 5,
      "rented": []
    },
    {
      "fName": "Ron",
      "lName": "Weasley",
      "idNumber": "3333",
      "phoneNumber": "333 333 3333",
      "email": "RW@hogwarts.ca",
      "password": "1234",
      "rating": 5,
      "rented": []
    },
    {
      "fName": "C",
      "lName": "B",
      "idNumber": "11",
      "phoneNumber": "123 456 7890",
      "email": "CB@email.com",
      "password": "1234",
      "rented": []
    }
  ],
  "Owners": [
    {
      "fName": "Peter",
      "lName": "Kosa",
      "idNumber": "8787",
      "phoneNumber": "300 400 5050",
      "email": "peter@email.com",
      "password": "password",
      "rating": 5,
      "properties": []
    },
    {
      "fName": "Pedro",
      "lName": "Ferreira",
      "idNumber": "9999",
      "phoneNumber": "300 400 5050",
      "email": "pedro@here.com",
      "password": "1234",
      "rating": 5,
      "properties": []
    },
    {
      "fName": "Albus",
      "lName": "Dumbledore",
      "idNumber": "77777",
      "phoneNumber": "555 555 5555",
      "email": "dumbledore@hogwarts.com",
      "password": "1234",
      "rating": 5,
      "properties": []
    },
    {
      "fName": "Minerva",
      "lName": "McGonagall",
      "idNumber": "55555",
      "phoneNumber": "555 555 5555",
      "email": "minerva@hogwarts.com",
      "password": "1234",
      "rating": 5,
      "properties": []
    },
    {
      "fName": "Elon",
      "lName": "Musk",
      "idNumber": "9002",
      "phoneNumber": "555 555 5555",
      "email": "elon@tesla.com",
      "password": "musk",
      "rating": 5,
      "properties": [
        {
          "name": "Tesla HQ California",
          "address": "CA, USA",
          "type": "????",
          "park": "yes",
          "transport": "yes",
          "smoking": "no",
          "seats": "15",
          "availabilityFrom": "2022-04-22",
          "availabilityTo": "",
          "leaseterm": "day",
          "price": "500",
          "workspaces": [
            {
              "id": "UHcFFMRQ9",
              "name": "San Francisco",
              "type": "open-desk",
              "smoking": "yes",
              "seats": "5",
              "availability": "2022-04-24",
              "leaseterm": "month",
              "price": "66.9",
              "listed": "yes",
              "rating": 1
            },
            {
              "id": "d3xDbdt7v",
              "name": "Santa Monica",
              "type": "private-workspace",
              "smoking": "no",
              "seats": "3",
              "availability": "2022-04-24",
              "leaseterm": "day",
              "price": "777",
              "listed": "yes",
              "rating": 3
            }
          ]
        },
        {
          "name": "Tesla HQ Texas",
          "address": "CA, USA",
          "type": "????",
          "park": "yes",
          "transport": "yes",
          "smoking": "no",
          "seats": "15",
          "availabilityFrom": "2022-04-22",
          "availabilityTo": "",
          "leaseterm": "day",
          "price": "500",
          "workspaces": [
            {
              "id": "BySr3EDbh",
              "name": "Dallas",
              "type": "private-workspace",
              "smoking": "no",
              "seats": "5",
              "availability": "2022-04-30",
              "leaseterm": "month",
              "price": "1003",
              "listed": "no",
              "rating": 0
            },
            {
              "id": "1JxgN99TR",
              "name": "Houston",
              "type": "open-desk",
              "smoking": "yes",
              "seats": "7",
              "availability": "2022-04-30",
              "leaseterm": "week",
              "price": "741",
              "listed": "yes",
              "rating": 0
            }
          ]
        }
      ]
    },
    {
      "fName": "Severus",
      "lName": "Snape",
      "idNumber": "2222",
      "phoneNumber": "222 222 2222",
      "email": "SS@hogwarts.ca",
      "password": "1234",
      "rating": 5,
      "properties": [
        {
          "name": "This is a test",
          "address": "123 Fake Ave",
          "type": "????",
          "park": "yes",
          "transport": "yes",
          "smoking": "no",
          "seats": "20",
          "availabilityFrom": "2022-04-23",
          "availabilityTo": "2022-04-30",
          "leaseterm": "week",
          "price": "300",
          "workspaces": [
            {
              "id": "ShL7prSrS",
              "name": "Yet another test",
              "type": "meeting-room",
              "smoking": "no",
              "seats": "4",
              "availability": "2022-04-23",
              "leaseterm": "week",
              "price": "800",
              "listed": "yes"
            },
            {
              "id": "ILs4UBRAH",
              "name": "Blah blah",
              "type": "meeting-room",
              "smoking": "yes",
              "seats": "8",
              "availability": "2022-04-02",
              "leaseterm": "month",
              "price": "900",
              "listed": "yes"
            }
          ]
        },
        {
          "name": "Another test",
          "address": "123 Fake Ave",
          "type": "????",
          "park": "no",
          "transport": "no",
          "smoking": "no",
          "seats": "32",
          "availabilityFrom": "2022-04-09",
          "availabilityTo": "2022-04-30",
          "leaseterm": "month",
          "price": "600",
          "workspaces": []
        },
        {
          "name": "Another test",
          "address": "123 Fake Ave",
          "type": "????",
          "park": "no",
          "transport": "no",
          "smoking": "no",
          "seats": "39",
          "availabilityFrom": "2022-04-02",
          "availabilityTo": "2022-04-30",
          "leaseterm": "month",
          "price": "321",
          "workspaces": []
        },
        {
          "name": "final test",
          "address": "123 Fake Ave",
          "type": "????",
          "park": "no",
          "transport": "no",
          "smoking": "no",
          "seats": "1",
          "availabilityFrom": "",
          "availabilityTo": "",
          "leaseterm": "day",
          "price": "322",
          "workspaces": []
        }
      ]
    },
    {
      "fName": "Jane",
      "lName": "Doe",
      "idNumber": "8888",
      "phoneNumber": "888 888 8888",
      "email": "JDoe@email.com",
      "password": "1234",
      "rating": 5,
      "properties": [
        {
          "name": "This is a test",
          "address": "123 Fake Ave",
          "type": "????",
          "park": "no",
          "transport": "no",
          "smoking": "no",
          "seats": "1",
          "availabilityFrom": "",
          "availabilityTo": "",
          "leaseterm": "day",
          "price": "600",
          "workspaces": [
            {
              "id": "TbBBwd4AQ",
              "name": "Yet another test",
              "type": "meeting-room",
              "smoking": "no",
              "seats": "1",
              "availability": "",
              "leaseterm": "day",
              "price": "900",
              "listed": "yes"
            }
          ]
        }
      ]
    }
  ]
}